atframework/__init__.py
atframework/apis/__init__.py
atframework/apis/at_gui_api.py
atframework/drivers/__init__.py
atframework/drivers/chromedriver
atframework/drivers/chromedriver-linux64
atframework/drivers/drivers_settings.py
atframework/drivers/geckodriver
atframework/drivers/geckodriver-linux64
atframework/model/__init__.py
atframework/model/at_clear.py
atframework/model/at_click.py
atframework/model/at_closing.py
atframework/model/at_expand.py
atframework/model/at_get.py
atframework/model/at_opening.py
atframework/model/at_scroll.py
atframework/model/at_select.py
atframework/model/at_show.py
atframework/model/at_type.py
atframework/model/at_waiting.py
atframework/model/model.py
atframework/selenium/__init__.py
atframework/selenium/seleniumhq301.py
atframework/selenium/taiji.py
atframework/tools/__init__.py
atframework/tools/log/__init__.py
atframework/tools/log/config.py
atframework/tools/log/log.conf
atframework/tools/mail/__init__.py
atframework/tools/mail/mail.py
atframework/tools/mail/mail_settings.py
atframework/utils/__init__.py
atframework/utils/properties.py
atframework/utils/utils.py
atframework/utils/xmlrunner.py
atframework-0.2.0.6.dist-info/LICENSE
atframework-0.2.0.6.dist-info/METADATA
atframework-0.2.0.6.dist-info/WHEEL
atframework-0.2.0.6.dist-info/top_level.txt
atframework-0.2.0.6.dist-info/RECORD
