Metadata-Version: 2.1
Name: atframework
Version: 0.2.0.6
Summary: The automation framework base on selenium
Home-page: https://github.com/pypa/sampleproject
Author: Siro
Author-email: sirodeng@gmail.com
License: UNKNOWN
Project-URL: Bug Tracker, https://github.com/pypa/sampleproject/issues
Platform: UNKNOWN
Classifier: Programming Language :: Python :: 3
Classifier: License :: OSI Approved :: MIT License
Classifier: Operating System :: OS Independent
Requires-Python: >=3.5:
License-File: LICENSE
